README.txt
setup.py
SESAR_Web_Services_Library.egg-info/PKG-INFO
SESAR_Web_Services_Library.egg-info/SOURCES.txt
SESAR_Web_Services_Library.egg-info/dependency_links.txt
SESAR_Web_Services_Library.egg-info/not-zip-safe
SESAR_Web_Services_Library.egg-info/requires.txt
SESAR_Web_Services_Library.egg-info/top_level.txt
sesarwslib/__init__.py
sesarwslib/categories.py
sesarwslib/sesarwsclient.py
sesarwslib/sample/Sample.py
sesarwslib/sample/__init__.py