Metadata-Version: 1.0
Name: SESAR-Web-Services-Library
Version: 0.9
Summary: SESAR web services library for IGSN management.
Home-page: https://github.com/Adam-Brown/SESAR-Web-Services-Lib
Author: Adam David Brown
Author-email: adam.brown@evbane.com
License: MIT
Platform: UNKNOWN
